setup.cfg
setup.py
launchkey_twisted/__init__.py
launchkey_twisted/twisted_api.py
launchkey_twisted.egg-info/PKG-INFO
launchkey_twisted.egg-info/SOURCES.txt
launchkey_twisted.egg-info/dependency_links.txt
launchkey_twisted.egg-info/requires.txt
launchkey_twisted.egg-info/top_level.txt