Metadata-Version: 1.1
Name: launchkey-twisted
Version: 1.0.0
Summary: LaunchKey Asynchronous SDK for Twisted
Home-page: https://launchkey.com
Author: LaunchKey
Author-email: support@launchkey.com
License: MIT
Platform: UNKNOWN
Classifier: Programming Language :: Python
Classifier: Framework :: Twisted
Classifier: Intended Audience :: Developers
Classifier: Operating System :: OS Independent
Classifier: Topic :: Software Development :: Libraries :: Python Modules
